{
  "timestamp": "2026-02-11T05:18:09Z",
  "data": [
    {
      "id": "bitcoin",
      "symbol": "btc",
      "name": "Bitcoin",
      "current_price": 67720,
      "price_change_percentage_1h": null,
      "price_change_percentage_24h": -2.70354,
      "total_volume": 44204794678,
      "market_cap": 1352873187450,
      "last_updated": "2026-02-11T05:18:00.523Z"
    },
    {
      "id": "ethereum",
      "symbol": "eth",
      "name": "Ethereum",
      "current_price": 1978.31,
      "price_change_percentage_1h": null,
      "price_change_percentage_24h": -4.32922,
      "total_volume": 23586567587,
      "market_cap": 238486466280,
      "last_updated": "2026-02-11T05:18:00.376Z"
    },
    {
      "id": "tether",
      "symbol": "usdt",
      "name": "Tether",
      "current_price": 0.999494,
      "price_change_percentage_1h": null,
      "price_change_percentage_24h": 0.01128,
      "total_volume": 74055807021,
      "market_cap": 184289679025,
      "last_updated": "2026-02-11T05:18:02.824Z"
    },
    {
      "id": "ripple",
      "symbol": "xrp",
      "name": "XRP",
      "current_price": 1.39,
      "price_change_percentage_1h": null,
      "price_change_percentage_24h": -3.87249,
      "total_volume": 2390598692,
      "market_cap": 84477488131,
      "last_updated": "2026-02-11T05:18:01.546Z"
    },
    {
      "id": "binancecoin",
      "symbol": "bnb",
      "name": "BNB",
      "current_price": 611.96,
      "price_change_percentage_1h": null,
      "price_change_percentage_24h": -3.81964,
      "total_volume": 1176774089,
      "market_cap": 83340161029,
      "last_updated": "2026-02-11T05:18:00.383Z"
    },
    {
      "id": "usd-coin",
      "symbol": "usdc",
      "name": "USDC",
      "current_price": 0.999909,
      "price_change_percentage_1h": null,
      "price_change_percentage_24h": -0.00027,
      "total_volume": 8500429528,
      "market_cap": 73293221056,
      "last_updated": "2026-02-11T05:18:03.243Z"
    },
    {
      "id": "solana",
      "symbol": "sol",
      "name": "Solana",
      "current_price": 82.24,
      "price_change_percentage_1h": null,
      "price_change_percentage_24h": -4.73397,
      "total_volume": 3598511625,
      "market_cap": 46607417173,
      "last_updated": "2026-02-11T05:18:01.749Z"
    },
    {
      "id": "tron",
      "symbol": "trx",
      "name": "TRON",
      "current_price": 0.275599,
      "price_change_percentage_1h": null,
      "price_change_percentage_24h": -0.75578,
      "total_volume": 520296082,
      "market_cap": 26107131151,
      "last_updated": "2026-02-11T05:18:02.830Z"
    },
    {
      "id": "figure-heloc",
      "symbol": "figr_heloc",
      "name": "Figure Heloc",
      "current_price": 1.032,
      "price_change_percentage_1h": null,
      "price_change_percentage_24h": -0.13984,
      "total_volume": 28732018,
      "market_cap": 15549052648,
      "last_updated": "2026-02-11T05:18:06.634Z"
    },
    {
      "id": "dogecoin",
      "symbol": "doge",
      "name": "Dogecoin",
      "current_price": 0.092155,
      "price_change_percentage_1h": null,
      "price_change_percentage_24h": -3.33871,
      "total_volume": 835693525,
      "market_cap": 15518169150,
      "last_updated": "2026-02-11T05:18:06.355Z"
    },
    {
      "id": "whitebit",
      "symbol": "wbt",
      "name": "WhiteBIT Coin",
      "current_price": 50.99,
      "price_change_percentage_1h": null,
      "price_change_percentage_24h": -2.94999,
      "total_volume": 102263732,
      "market_cap": 10895941144,
      "last_updated": "2026-02-11T05:18:03.132Z"
    },
    {
      "id": "bitcoin-cash",
      "symbol": "bch",
      "name": "Bitcoin Cash",
      "current_price": 518.88,
      "price_change_percentage_1h": null,
      "price_change_percentage_24h": -1.09864,
      "total_volume": 334127330,
      "market_cap": 10361747343,
      "last_updated": "2026-02-11T05:18:05.420Z"
    },
    {
      "id": "usds",
      "symbol": "usds",
      "name": "USDS",
      "current_price": 0.999942,
      "price_change_percentage_1h": null,
      "price_change_percentage_24h": 0.07483,
      "total_volume": 3714309,
      "market_cap": 9564414288,
      "last_updated": "2026-02-11T05:18:02.883Z"
    },
    {
      "id": "cardano",
      "symbol": "ada",
      "name": "Cardano",
      "current_price": 0.259512,
      "price_change_percentage_1h": null,
      "price_change_percentage_24h": -2.95342,
      "total_volume": 357509118,
      "market_cap": 9536414892,
      "last_updated": "2026-02-11T05:18:05.647Z"
    },
    {
      "id": "leo-token",
      "symbol": "leo",
      "name": "LEO Token",
      "current_price": 8.23,
      "price_change_percentage_1h": null,
      "price_change_percentage_24h": -4.29074,
      "total_volume": 939461,
      "market_cap": 7586046661,
      "last_updated": "2026-02-11T05:18:08.066Z"
    },
    {
      "id": "hyperliquid",
      "symbol": "hype",
      "name": "Hyperliquid",
      "current_price": 29.23,
      "price_change_percentage_1h": null,
      "price_change_percentage_24h": -5.04442,
      "total_volume": 305649018,
      "market_cap": 6943915100,
      "last_updated": "2026-02-11T05:18:07.989Z"
    },
    {
      "id": "ethena-usde",
      "symbol": "usde",
      "name": "Ethena USDe",
      "current_price": 0.998721,
      "price_change_percentage_1h": null,
      "price_change_percentage_24h": 0.03009,
      "total_volume": 59827514,
      "market_cap": 6421923590,
      "last_updated": "2026-02-11T05:18:06.554Z"
    },
    {
      "id": "monero",
      "symbol": "xmr",
      "name": "Monero",
      "current_price": 342.52,
      "price_change_percentage_1h": null,
      "price_change_percentage_24h": 1.50457,
      "total_volume": 98035704,
      "market_cap": 6314866377,
      "last_updated": "2026-02-11T05:18:08.815Z"
    },
    {
      "id": "canton-network",
      "symbol": "cc",
      "name": "Canton",
      "current_price": 0.165303,
      "price_change_percentage_1h": null,
      "price_change_percentage_24h": -2.60269,
      "total_volume": 10611971,
      "market_cap": 6237120198,
      "last_updated": "2026-02-11T05:18:05.233Z"
    },
    {
      "id": "chainlink",
      "symbol": "link",
      "name": "Chainlink",
      "current_price": 8.41,
      "price_change_percentage_1h": null,
      "price_change_percentage_24h": -3.3327,
      "total_volume": 303624232,
      "market_cap": 5961255866,
      "last_updated": "2026-02-11T05:18:05.676Z"
    }
  ]
}
